[
  {
    "idCard": "",
    "idReservation": "",
    "car": "",
    "dateDebut": "",
    "dateFin": "",
    "prix": ""
  },
  {
    "idCard": "HH112666",
    "idReservation": "1",
    "car": "Dodge",
    "dateDebut": "2020-04-05",
    "dateFin": "2020-04-29",
    "prix": "888"
  },
  {
    "idCard": "HH112311",
    "idReservation": "2",
    "car": "Dodge",
    "dateDebut": "2020-04-16",
    "dateFin": "2020-04-30",
    "prix": "518"
  },
  {
    "idCard": "HH112311",
    "idReservation": "3",
    "car": "Dodge",
    "dateDebut": "2020-04-22",
    "dateFin": "2020-04-29",
    "prix": "259"
  },
  {
    "idCard": "HH112311",
    "idReservation": 4,
    "car": "Dodge",
    "dateDebut": "2020-04-22",
    "dateFin": "2020-04-29",
    "prix": "259"
  },
  {
    "idCard": "HH112311",
    "idReservation": 5,
    "car": "GMC",
    "dateDebut": "2020-04-22",
    "dateFin": "2020-04-29",
    "prix": "259"
  },
  {
    "idCard": "HH112311",
    "idReservation": 6,
    "car": "Audi",
    "dateDebut": "2020-04-22",
    "dateFin": "2020-05-20",
    "prix": "576"
  },
  {
    "idCard": "HH112311",
    "idReservation": 7,
    "car": "Dodge",
    "dateDebut": "2020-04-23",
    "dateFin": "2020-04-30",
    "prix": "259"
  }
]